setup.cfg
setup.py
bonspy/__init__.py
bonspy/bonsai.py
bonspy/features.py
bonspy/graph_builder.py
bonspy/logistic.py
bonspy/utils.py
bonspy.egg-info/PKG-INFO
bonspy.egg-info/SOURCES.txt
bonspy.egg-info/dependency_links.txt
bonspy.egg-info/top_level.txt
bonspy/tests/data/test.csv.gz