Metadata-Version: 1.1
Name: bonspy
Version: 1.2.7
Summary: Library that converts bidding trees to the AppNexus Bonsai language.
Home-page: https://github.com/markovianhq/bonspy
Author: Alexander Volkmann, Georg Walther
Author-email: contact@markovian.com
License: UNKNOWN
Download-URL: https://github.com/markovianhq/bonspy/tarball/master
Platform: UNKNOWN
Classifier: Development Status :: 3 - Alpha
Classifier: License :: OSI Approved :: BSD License
Classifier: Programming Language :: Python :: 3
